LICENSE
LICENSE.MIT
LICENSE.apache
LICENSE.tinycthread
LICENSE.unlzw
MANIFEST.in
README.rst
setup.py
atrip/__init__.py
atrip/_metadata.py
atrip/_version.py
atrip/archiver.py
atrip/assembler.py
atrip/cartridge.py
atrip/char_mapping.py
atrip/collection.py
atrip/compressor.py
atrip/container.py
atrip/disassembler.py
atrip/errors.py
atrip/executables.py
atrip/file_type.py
atrip/filesystem.py
atrip/magic.py
atrip/mame.py
atrip/media_type.py
atrip/memory_map.py
atrip/omnivore_loader.py
atrip/segment.py
atrip/signature.py
atrip/standard_delivery.py
atrip/stringifier.py
atrip/style_bits.py
atrip/utils.py
atrip/archivers/__init__.py
atrip/archivers/tar.py
atrip/archivers/zip.py
atrip/assemblers/__init__.py
atrip/assemblers/mac65.py
atrip/compressors/__init__.py
atrip/compressors/bzip.py
atrip/compressors/dcm.py
atrip/compressors/gzip.py
atrip/compressors/lz4.py
atrip/compressors/lzma.py
atrip/compressors/unix_compress.py
atrip/compressors/zlib.py
atrip/disassemblers/__init__.py
atrip/disassemblers/cputables.py
atrip/disassemblers/disasm.py
atrip/disassemblers/dtypes.py
atrip/disassemblers/flags.py
atrip/disassemblers/history.py
atrip/disassemblers/miniasm.py
atrip/disassemblers/valid_cpus.py
atrip/file_types/__init__.py
atrip/file_types/apple_dos33_bsave.py
atrip/file_types/atari_xex.py
atrip/filesystems/__init__.py
atrip/filesystems/apple_dos33.py
atrip/filesystems/atari_cas.py
atrip/filesystems/atari_dos2.py
atrip/filesystems/atari_jumpman.py
atrip/filesystems/dummy.py
atrip/filesystems/fstbt.py
atrip/filesystems/kboot.py
atrip/filesystems/mydos.py
atrip/filesystems/spartados.py
atrip/machines/__init__.py
atrip/machines/atari8bit/__init__.py
atrip/machines/atari8bit/jumpman/__init__.py
atrip/machines/atari8bit/jumpman/parser.py
atrip/machines/atari8bit/jumpman/playfield.py
atrip/media_types/__init__.py
atrip/media_types/apple_disks.py
atrip/media_types/atari_carts.py
atrip/media_types/atari_disks.py
atrip/media_types/atari_tapes.py
atrip/signatures/__init__.py
omnivore.egg-info/PKG-INFO
omnivore.egg-info/SOURCES.txt
omnivore.egg-info/dependency_links.txt
omnivore.egg-info/entry_points.txt
omnivore.egg-info/not-zip-safe
omnivore.egg-info/requires.txt
omnivore.egg-info/top_level.txt
