Metadata-Version: 1.2
Name: omnivore
Version: 1.99.9
Summary: Unified front-end providing common interface to control several 8 bit emulators
Home-page: https://github.com/robmcmullen/omnivore
Author: Rob McMullen
Author-email: feedback@playermissile.com
License: UNKNOWN
Platform: Windows
Platform: Linux
Platform: Mac OS-X
Platform: Unix
Classifier: Development Status :: 5 - Production/Stable
Classifier: Intended Audience :: Developers
Classifier: License :: OSI Approved :: GNU General Public License (GPL)
Classifier: Operating System :: MacOS
Classifier: Operating System :: Microsoft :: Windows
Classifier: Operating System :: OS Independent
Classifier: Operating System :: POSIX
Classifier: Operating System :: Unix
Classifier: Programming Language :: Python
Classifier: Topic :: Utilities
Classifier: Topic :: Software Development :: Assemblers
Requires-Python: >=3.6
